brewer2mpl/__init__.py
brewer2mpl/brewer2mpl.py
brewer2mpl/diverging.py
brewer2mpl/qualitative.py
brewer2mpl/sequential.py
brewer2mpl/data/colorbrewer_all_schemes.csv
brewer2mpl/data/colorbrewer_all_schemes.json
brewer2mpl/data/colorbrewer_licence.txt
brewer2mpl/data/colorbrewer_schemes_csv_to_json.py
brewer2mpl/wesanderson/__init__.py
brewer2mpl/wesanderson/wesanderson.py
brewer2mpl-1.4.dist-info/DESCRIPTION.rst
brewer2mpl-1.4.dist-info/METADATA
brewer2mpl-1.4.dist-info/metadata.json
brewer2mpl-1.4.dist-info/RECORD
brewer2mpl-1.4.dist-info/top_level.txt
brewer2mpl-1.4.dist-info/WHEEL
