Metadata-Version: 2.0
Name: brewer2mpl
Version: 1.4
Summary: Connect colorbrewer2.org color maps to Python and matplotlib
Home-page: https://github.com/jiffyclub/brewer2mpl/wiki
Author: Matt Davis
Author-email: jiffyclub@gmail.com
License: UNKNOWN
Platform: UNKNOWN
Classifier: License :: OSI Approved :: MIT License
Classifier: Programming Language :: Python
Classifier: Programming Language :: Python :: 2.6
Classifier: Programming Language :: Python :: 2.7
Classifier: Programming Language :: Python :: 3
Classifier: Topic :: Scientific/Engineering :: Visualization
